sandesh/__init__.py
sandesh/send.py
sandesh-0.3.2.dist-info/LICENSE
sandesh-0.3.2.dist-info/METADATA
sandesh-0.3.2.dist-info/WHEEL
sandesh-0.3.2.dist-info/top_level.txt
sandesh-0.3.2.dist-info/RECORD
