Metadata-Version: 2.1
Name: sandesh
Version: 0.3.2
Summary: sandesh - a simple app to send messages on slack
Home-page: https://github.com/abhishekkrthakur/sandesh
Author: Abhishek Thakur
License: MIT License
Platform: linux
Platform: unix
Requires-Python: >=3.7
License-File: LICENSE
Requires-Dist: loguru
